{
  "project_info": {
    "project_number": "347269442381",
    "project_id": "tasksync-ba692",
    "storage_bucket": "tasksync-ba692.firebasestorage.app"
  },
  "client": [
    {
      "client_info": {
        "mobilesdk_app_id": "1:347269442381:android:76fc6f7851aa0acc982504",
        "android_client_info": {
          "package_name": "com.rahul.tasksync"
        }
      },
      "oauth_client": [],
      "api_key": [
        {
          "current_key": "AIzaSyDgCryqsRrMvMtUwN2wtoGfXby-nIrawzw"
        }
      ],
      "services": {
        "appinvite_service": {
          "other_platform_oauth_client": []
        }
      }
    }
  ],
  "configuration_version": "1"
}
